{
  "grq": [
    {
      "enabled": true,
      "job_type": "hysds-io-purge_ISL:__TAG__",
      "kwargs": "{}",
      "passthru_query": false,
      "priority": 0,
      "query_all": false,
      "query_string": "{\n  \"bool\": {\n    \"must\": [\n      {\n        \"exists\": {\n          \"field\": \"metadata.ISL_urls\"\n        }\n      }\n    ]\n  }\n}",
      "queue": "opera-job_worker-small",
      "rule_name": "trigger-purge-ISL",
      "username": "hysdsops",
      "workflow": "hysds-io-purge_ISL:__TAG__",
      "job_spec": "job-purge_ISL:__TAG__"
    },
    {
      "enabled": true,
      "job_type": "hysds-io-SCIFLO_L3_DSWx_HLS:__TAG__",
      "kwargs": "{}",
      "passthru_query": false,
      "priority": 0,
      "query_all": false,
      "query_string": "{\"bool\":{\"must\":[{\"term\":{\"dataset_type.keyword\":\"L2_HLS_L30-state-config\"}},{\"bool\":{\"must\":[{\"exists\":{\"field\":\"metadata.B02\"}},{\"exists\":{\"field\":\"metadata.B03\"}},{\"exists\":{\"field\":\"metadata.B04\"}},{\"exists\":{\"field\":\"metadata.B05\"}},{\"exists\":{\"field\":\"metadata.B06\"}},{\"exists\":{\"field\":\"metadata.B07\"}},{\"exists\":{\"field\":\"metadata.Fmask\"}}]}}]}}",
      "queue": "opera-job_worker-small",
      "rule_name": "trigger-SCIFLO_L3_DSWx_HLS",
      "username": "hysdsops",
      "workflow": "hysds-io-SCIFLO_L3_DSWx_HLS:__TAG__",
      "job_spec": "job-SCIFLO_L3_DSWx_HLS:__TAG__"
    },
    {
      "enabled": true,
      "job_type": "hysds-io-SCIFLO_L3_DSWx_HLS_STATE_CONFIG:__TAG__",
      "kwargs": "{}",
      "passthru_query": false,
      "priority": 0,
      "query_all": false,
      "query_string": "{\"bool\": {\"should\": [{\"terms\": {\"dataset_type.keyword\": [\"L2_HLS_L30\",\"L2_HLS_S30\"]}}]}}",
      "queue": "opera-job_worker-small",
      "rule_name": "trigger-SCIFLO_L3_DSWx_HLS_STATE_CONFIG",
      "username": "hysdsops",
      "workflow": "hysds-io-SCIFLO_L3_DSWx_HLS_STATE_CONFIG:__TAG__",
      "job_spec": "job-SCIFLO_L3_DSWx_HLS_STATE_CONFIG:__TAG__"
    }
  ],
  "mozart": []
}
